{"frames": [

{
	"filename": "gui_construct_zho_build09.png",
	"frame": {"x":447,"y":567,"w":38,"h":38},
	"rotated": false,
	"trimmed": false,
	"spriteSourceSize": {"x":0,"y":0,"w":38,"h":38},
	"sourceSize": {"w":38,"h":38},
	"pivot": {"x":0.5,"y":0.5}
},
{
	"filename": "gui_ico_zho_build09.png",
	"frame": {"x":259,"y":826,"w":118,"h":81},
	"rotated": false,
	"trimmed": true,
	"spriteSourceSize": {"x":3,"y":16,"w":118,"h":81},
	"sourceSize": {"w":127,"h":111},
	"pivot": {"x":0.5,"y":0.5}
},
{
	"filename": "gui_ico_zho_sm_build09.png",
	"frame": {"x":394,"y":567,"w":51,"h":51},
	"rotated": false,
	"trimmed": false,
	"spriteSourceSize": {"x":0,"y":0,"w":51,"h":51},
	"sourceSize": {"w":51,"h":51},
	"pivot": {"x":0.5,"y":0.5}
},
{
	"filename": "zho_build09_00000.png",
	"frame": {"x":1,"y":1,"w":129,"h":100},
	"rotated": false,
	"trimmed": true,
	"spriteSourceSize": {"x":83,"y":103,"w":129,"h":100},
	"sourceSize": {"w":300,"h":300},
	"pivot": {"x":0.5,"y":0.5}
},
{
	"filename": "zho_build09_00001.png",
	"frame": {"x":132,"y":1,"w":129,"h":100},
	"rotated": false,
	"trimmed": true,
	"spriteSourceSize": {"x":83,"y":103,"w":129,"h":100},
	"sourceSize": {"w":300,"h":300},
	"pivot": {"x":0.5,"y":0.5}
},
{
	"filename": "zho_build09_00002.png",
	"frame": {"x":263,"y":1,"w":129,"h":100},
	"rotated": false,
	"trimmed": true,
	"spriteSourceSize": {"x":83,"y":103,"w":129,"h":100},
	"sourceSize": {"w":300,"h":300},
	"pivot": {"x":0.5,"y":0.5}
},
{
	"filename": "zho_build09_00003.png",
	"frame": {"x":1,"y":103,"w":129,"h":100},
	"rotated": false,
	"trimmed": true,
	"spriteSourceSize": {"x":83,"y":103,"w":129,"h":100},
	"sourceSize": {"w":300,"h":300},
	"pivot": {"x":0.5,"y":0.5}
},
{
	"filename": "zho_build09_00004.png",
	"frame": {"x":132,"y":103,"w":129,"h":100},
	"rotated": false,
	"trimmed": true,
	"spriteSourceSize": {"x":83,"y":103,"w":129,"h":100},
	"sourceSize": {"w":300,"h":300},
	"pivot": {"x":0.5,"y":0.5}
},
{
	"filename": "zho_build09_00005.png",
	"frame": {"x":263,"y":103,"w":129,"h":100},
	"rotated": false,
	"trimmed": true,
	"spriteSourceSize": {"x":83,"y":103,"w":129,"h":100},
	"sourceSize": {"w":300,"h":300},
	"pivot": {"x":0.5,"y":0.5}
},
{
	"filename": "zho_build09_00006.png",
	"frame": {"x":1,"y":205,"w":129,"h":100},
	"rotated": false,
	"trimmed": true,
	"spriteSourceSize": {"x":83,"y":103,"w":129,"h":100},
	"sourceSize": {"w":300,"h":300},
	"pivot": {"x":0.5,"y":0.5}
},
{
	"filename": "zho_build09_00007.png",
	"frame": {"x":132,"y":205,"w":129,"h":100},
	"rotated": false,
	"trimmed": true,
	"spriteSourceSize": {"x":83,"y":103,"w":129,"h":100},
	"sourceSize": {"w":300,"h":300},
	"pivot": {"x":0.5,"y":0.5}
},
{
	"filename": "zho_build09_00008.png",
	"frame": {"x":263,"y":205,"w":129,"h":100},
	"rotated": false,
	"trimmed": true,
	"spriteSourceSize": {"x":83,"y":103,"w":129,"h":100},
	"sourceSize": {"w":300,"h":300},
	"pivot": {"x":0.5,"y":0.5}
},
{
	"filename": "zho_build09_00009.png",
	"frame": {"x":1,"y":307,"w":129,"h":100},
	"rotated": false,
	"trimmed": true,
	"spriteSourceSize": {"x":83,"y":103,"w":129,"h":100},
	"sourceSize": {"w":300,"h":300},
	"pivot": {"x":0.5,"y":0.5}
},
{
	"filename": "zho_build09_00010.png",
	"frame": {"x":132,"y":307,"w":129,"h":100},
	"rotated": false,
	"trimmed": true,
	"spriteSourceSize": {"x":83,"y":103,"w":129,"h":100},
	"sourceSize": {"w":300,"h":300},
	"pivot": {"x":0.5,"y":0.5}
},
{
	"filename": "zho_build09_00011.png",
	"frame": {"x":263,"y":307,"w":129,"h":100},
	"rotated": false,
	"trimmed": true,
	"spriteSourceSize": {"x":83,"y":103,"w":129,"h":100},
	"sourceSize": {"w":300,"h":300},
	"pivot": {"x":0.5,"y":0.5}
},
{
	"filename": "zho_build09_00012.png",
	"frame": {"x":1,"y":409,"w":129,"h":100},
	"rotated": false,
	"trimmed": true,
	"spriteSourceSize": {"x":83,"y":103,"w":129,"h":100},
	"sourceSize": {"w":300,"h":300},
	"pivot": {"x":0.5,"y":0.5}
},
{
	"filename": "zho_build09_00013.png",
	"frame": {"x":132,"y":409,"w":129,"h":100},
	"rotated": false,
	"trimmed": true,
	"spriteSourceSize": {"x":83,"y":103,"w":129,"h":100},
	"sourceSize": {"w":300,"h":300},
	"pivot": {"x":0.5,"y":0.5}
},
{
	"filename": "zho_build09_00014.png",
	"frame": {"x":263,"y":409,"w":129,"h":100},
	"rotated": false,
	"trimmed": true,
	"spriteSourceSize": {"x":83,"y":103,"w":129,"h":100},
	"sourceSize": {"w":300,"h":300},
	"pivot": {"x":0.5,"y":0.5}
},
{
	"filename": "zho_build09_00015.png",
	"frame": {"x":1,"y":511,"w":129,"h":100},
	"rotated": false,
	"trimmed": true,
	"spriteSourceSize": {"x":83,"y":103,"w":129,"h":100},
	"sourceSize": {"w":300,"h":300},
	"pivot": {"x":0.5,"y":0.5}
},
{
	"filename": "zho_build09_00016.png",
	"frame": {"x":132,"y":511,"w":129,"h":100},
	"rotated": false,
	"trimmed": true,
	"spriteSourceSize": {"x":83,"y":103,"w":129,"h":100},
	"sourceSize": {"w":300,"h":300},
	"pivot": {"x":0.5,"y":0.5}
},
{
	"filename": "zho_build09_00017.png",
	"frame": {"x":263,"y":511,"w":129,"h":100},
	"rotated": false,
	"trimmed": true,
	"spriteSourceSize": {"x":83,"y":103,"w":129,"h":100},
	"sourceSize": {"w":300,"h":300},
	"pivot": {"x":0.5,"y":0.5}
},
{
	"filename": "zho_build09_00018.png",
	"frame": {"x":1,"y":613,"w":129,"h":100},
	"rotated": false,
	"trimmed": true,
	"spriteSourceSize": {"x":83,"y":103,"w":129,"h":100},
	"sourceSize": {"w":300,"h":300},
	"pivot": {"x":0.5,"y":0.5}
},
{
	"filename": "zho_build09_00019.png",
	"frame": {"x":132,"y":613,"w":129,"h":100},
	"rotated": false,
	"trimmed": true,
	"spriteSourceSize": {"x":83,"y":103,"w":129,"h":100},
	"sourceSize": {"w":300,"h":300},
	"pivot": {"x":0.5,"y":0.5}
},
{
	"filename": "zho_build09_born_00000.png",
	"frame": {"x":394,"y":391,"w":92,"h":93},
	"rotated": false,
	"trimmed": true,
	"spriteSourceSize": {"x":104,"y":88,"w":92,"h":93},
	"sourceSize": {"w":300,"h":300},
	"pivot": {"x":0.5,"y":0.5}
},
{
	"filename": "zho_build09_born_00001.png",
	"frame": {"x":394,"y":117,"w":110,"h":102},
	"rotated": false,
	"trimmed": true,
	"spriteSourceSize": {"x":95,"y":88,"w":110,"h":102},
	"sourceSize": {"w":300,"h":300},
	"pivot": {"x":0.5,"y":0.5}
},
{
	"filename": "zho_build09_born_00002.png",
	"frame": {"x":263,"y":715,"w":116,"h":109},
	"rotated": false,
	"trimmed": true,
	"spriteSourceSize": {"x":92,"y":89,"w":116,"h":109},
	"sourceSize": {"w":300,"h":300},
	"pivot": {"x":0.5,"y":0.5}
},
{
	"filename": "zho_build09_born_00003.png",
	"frame": {"x":394,"y":1,"w":112,"h":114},
	"rotated": false,
	"trimmed": true,
	"spriteSourceSize": {"x":94,"y":92,"w":112,"h":114},
	"sourceSize": {"w":300,"h":300},
	"pivot": {"x":0.5,"y":0.5}
},
{
	"filename": "zho_build09_born_00004.png",
	"frame": {"x":381,"y":715,"w":120,"h":104},
	"rotated": false,
	"trimmed": true,
	"spriteSourceSize": {"x":90,"y":97,"w":120,"h":104},
	"sourceSize": {"w":300,"h":300},
	"pivot": {"x":0.5,"y":0.5}
},
{
	"filename": "zho_build09_born_00005.png",
	"frame": {"x":1,"y":1019,"w":122,"h":94},
	"rotated": false,
	"trimmed": true,
	"spriteSourceSize": {"x":89,"y":102,"w":122,"h":94},
	"sourceSize": {"w":300,"h":300},
	"pivot": {"x":0.5,"y":0.5}
},
{
	"filename": "zho_build09_born_00006.png",
	"frame": {"x":394,"y":308,"w":111,"h":81},
	"rotated": false,
	"trimmed": true,
	"spriteSourceSize": {"x":94,"y":109,"w":111,"h":81},
	"sourceSize": {"w":300,"h":300},
	"pivot": {"x":0.5,"y":0.5}
},
{
	"filename": "zho_build09_born_00007.png",
	"frame": {"x":394,"y":486,"w":107,"h":79},
	"rotated": false,
	"trimmed": true,
	"spriteSourceSize": {"x":91,"y":109,"w":107,"h":79},
	"sourceSize": {"w":300,"h":300},
	"pivot": {"x":0.5,"y":0.5}
},
{
	"filename": "zho_build09_born_00008.png",
	"frame": {"x":394,"y":221,"w":113,"h":85},
	"rotated": false,
	"trimmed": true,
	"spriteSourceSize": {"x":89,"y":108,"w":113,"h":85},
	"sourceSize": {"w":300,"h":300},
	"pivot": {"x":0.5,"y":0.5}
},
{
	"filename": "zho_build09_born_00009.png",
	"frame": {"x":377,"y":1021,"w":121,"h":92},
	"rotated": false,
	"trimmed": true,
	"spriteSourceSize": {"x":86,"y":106,"w":121,"h":92},
	"sourceSize": {"w":300,"h":300},
	"pivot": {"x":0.5,"y":0.5}
},
{
	"filename": "zho_build09_born_00010.png",
	"frame": {"x":263,"y":613,"w":129,"h":100},
	"rotated": false,
	"trimmed": true,
	"spriteSourceSize": {"x":83,"y":103,"w":129,"h":100},
	"sourceSize": {"w":300,"h":300},
	"pivot": {"x":0.5,"y":0.5}
},
{
	"filename": "zho_build09_withers_00000.png",
	"frame": {"x":1,"y":715,"w":129,"h":100},
	"rotated": false,
	"trimmed": true,
	"spriteSourceSize": {"x":83,"y":103,"w":129,"h":100},
	"sourceSize": {"w":300,"h":300},
	"pivot": {"x":0.5,"y":0.5}
},
{
	"filename": "zho_build09_withers_00001.png",
	"frame": {"x":132,"y":715,"w":129,"h":100},
	"rotated": false,
	"trimmed": true,
	"spriteSourceSize": {"x":83,"y":103,"w":129,"h":100},
	"sourceSize": {"w":300,"h":300},
	"pivot": {"x":0.5,"y":0.5}
},
{
	"filename": "zho_build09_withers_00002.png",
	"frame": {"x":1,"y":817,"w":127,"h":99},
	"rotated": false,
	"trimmed": true,
	"spriteSourceSize": {"x":84,"y":103,"w":127,"h":99},
	"sourceSize": {"w":300,"h":300},
	"pivot": {"x":0.5,"y":0.5}
},
{
	"filename": "zho_build09_withers_00003.png",
	"frame": {"x":130,"y":817,"w":127,"h":99},
	"rotated": false,
	"trimmed": true,
	"spriteSourceSize": {"x":84,"y":103,"w":127,"h":99},
	"sourceSize": {"w":300,"h":300},
	"pivot": {"x":0.5,"y":0.5}
},
{
	"filename": "zho_build09_withers_00004.png",
	"frame": {"x":381,"y":821,"w":126,"h":99},
	"rotated": false,
	"trimmed": true,
	"spriteSourceSize": {"x":85,"y":103,"w":126,"h":99},
	"sourceSize": {"w":300,"h":300},
	"pivot": {"x":0.5,"y":0.5}
},
{
	"filename": "zho_build09_withers_00005.png",
	"frame": {"x":1,"y":918,"w":125,"h":99},
	"rotated": false,
	"trimmed": true,
	"spriteSourceSize": {"x":86,"y":103,"w":125,"h":99},
	"sourceSize": {"w":300,"h":300},
	"pivot": {"x":0.5,"y":0.5}
},
{
	"filename": "zho_build09_withers_00006.png",
	"frame": {"x":128,"y":918,"w":124,"h":98},
	"rotated": false,
	"trimmed": true,
	"spriteSourceSize": {"x":86,"y":104,"w":124,"h":98},
	"sourceSize": {"w":300,"h":300},
	"pivot": {"x":0.5,"y":0.5}
},
{
	"filename": "zho_build09_withers_00007.png",
	"frame": {"x":254,"y":918,"w":124,"h":98},
	"rotated": false,
	"trimmed": true,
	"spriteSourceSize": {"x":86,"y":104,"w":124,"h":98},
	"sourceSize": {"w":300,"h":300},
	"pivot": {"x":0.5,"y":0.5}
},
{
	"filename": "zho_build09_withers_00008.png",
	"frame": {"x":380,"y":922,"w":124,"h":97},
	"rotated": false,
	"trimmed": true,
	"spriteSourceSize": {"x":86,"y":104,"w":124,"h":97},
	"sourceSize": {"w":300,"h":300},
	"pivot": {"x":0.5,"y":0.5}
},
{
	"filename": "zho_build09_withers_00009.png",
	"frame": {"x":128,"y":1018,"w":123,"h":97},
	"rotated": false,
	"trimmed": true,
	"spriteSourceSize": {"x":86,"y":104,"w":123,"h":97},
	"sourceSize": {"w":300,"h":300},
	"pivot": {"x":0.5,"y":0.5}
},
{
	"filename": "zho_build09_withers_00010.png",
	"frame": {"x":253,"y":1018,"w":122,"h":97},
	"rotated": false,
	"trimmed": true,
	"spriteSourceSize": {"x":87,"y":104,"w":122,"h":97},
	"sourceSize": {"w":300,"h":300},
	"pivot": {"x":0.5,"y":0.5}
}],
"meta": {
	"app": "http://www.codeandweb.com/texturepacker",
	"version": "1.0",
	"image": "zho_build09.png",
	"format": "RGBA8888",
	"size": {"w":508,"h":1116},
	"scale": "1",
	"smartupdate": "$TexturePacker:SmartUpdate:d022d3c4156ceb0d334492432d7376a5:44e78cad39414dcb83039fdae78534ad:1eb2ad5071ab080327b7f263d23f2b1e$"
}
}
