{"frames": [

{
	"filename": "gui_construct_zho_build10.png",
	"frame": {"x":194,"y":1255,"w":38,"h":38},
	"rotated": false,
	"trimmed": false,
	"spriteSourceSize": {"x":0,"y":0,"w":38,"h":38},
	"sourceSize": {"w":38,"h":38},
	"pivot": {"x":0.5,"y":0.5}
},
{
	"filename": "gui_ico_zho_build10.png",
	"frame": {"x":1,"y":444,"w":109,"h":108},
	"rotated": false,
	"trimmed": true,
	"spriteSourceSize": {"x":6,"y":0,"w":109,"h":108},
	"sourceSize": {"w":127,"h":111},
	"pivot": {"x":0.5,"y":0.5}
},
{
	"filename": "gui_ico_zho_sm_build10.png",
	"frame": {"x":194,"y":1202,"w":51,"h":51},
	"rotated": false,
	"trimmed": false,
	"spriteSourceSize": {"x":0,"y":0,"w":51,"h":51},
	"sourceSize": {"w":51,"h":51},
	"pivot": {"x":0.5,"y":0.5}
},
{
	"filename": "zho_build10_0000.png",
	"frame": {"x":1,"y":222,"w":109,"h":109},
	"rotated": false,
	"trimmed": true,
	"spriteSourceSize": {"x":95,"y":74,"w":109,"h":109},
	"sourceSize": {"w":300,"h":300},
	"pivot": {"x":0.5,"y":0.5}
},
{
	"filename": "zho_build10_born_0000.png",
	"frame": {"x":99,"y":1202,"w":93,"h":94},
	"rotated": false,
	"trimmed": true,
	"spriteSourceSize": {"x":103,"y":87,"w":93,"h":94},
	"sourceSize": {"w":300,"h":300},
	"pivot": {"x":0.5,"y":0.5}
},
{
	"filename": "zho_build10_born_0001.png",
	"frame": {"x":112,"y":991,"w":109,"h":103},
	"rotated": false,
	"trimmed": true,
	"spriteSourceSize": {"x":95,"y":87,"w":109,"h":103},
	"sourceSize": {"w":300,"h":300},
	"pivot": {"x":0.5,"y":0.5}
},
{
	"filename": "zho_build10_born_0002.png",
	"frame": {"x":1,"y":111,"w":115,"h":109},
	"rotated": false,
	"trimmed": true,
	"spriteSourceSize": {"x":92,"y":89,"w":115,"h":109},
	"sourceSize": {"w":300,"h":300},
	"pivot": {"x":0.5,"y":0.5}
},
{
	"filename": "zho_build10_born_0003.png",
	"frame": {"x":123,"y":109,"w":112,"h":113},
	"rotated": false,
	"trimmed": true,
	"spriteSourceSize": {"x":93,"y":92,"w":112,"h":113},
	"sourceSize": {"w":300,"h":300},
	"pivot": {"x":0.5,"y":0.5}
},
{
	"filename": "zho_build10_born_0004.png",
	"frame": {"x":1,"y":1,"w":120,"h":108},
	"rotated": false,
	"trimmed": true,
	"spriteSourceSize": {"x":89,"y":92,"w":120,"h":108},
	"sourceSize": {"w":300,"h":300},
	"pivot": {"x":0.5,"y":0.5}
},
{
	"filename": "zho_build10_born_0005.png",
	"frame": {"x":123,"y":1,"w":121,"h":106},
	"rotated": false,
	"trimmed": true,
	"spriteSourceSize": {"x":89,"y":89,"w":121,"h":106},
	"sourceSize": {"w":300,"h":300},
	"pivot": {"x":0.5,"y":0.5}
},
{
	"filename": "zho_build10_born_0006.png",
	"frame": {"x":1,"y":991,"w":109,"h":104},
	"rotated": false,
	"trimmed": true,
	"spriteSourceSize": {"x":95,"y":86,"w":109,"h":104},
	"sourceSize": {"w":300,"h":300},
	"pivot": {"x":0.5,"y":0.5}
},
{
	"filename": "zho_build10_born_0007.png",
	"frame": {"x":1,"y":1198,"w":96,"h":101},
	"rotated": false,
	"trimmed": true,
	"spriteSourceSize": {"x":101,"y":83,"w":96,"h":101},
	"sourceSize": {"w":300,"h":300},
	"pivot": {"x":0.5,"y":0.5}
},
{
	"filename": "zho_build10_born_0008.png",
	"frame": {"x":1,"y":1097,"w":99,"h":99},
	"rotated": false,
	"trimmed": true,
	"spriteSourceSize": {"x":98,"y":80,"w":99,"h":99},
	"sourceSize": {"w":300,"h":300},
	"pivot": {"x":0.5,"y":0.5}
},
{
	"filename": "zho_build10_born_0009.png",
	"frame": {"x":112,"y":1096,"w":104,"h":104},
	"rotated": false,
	"trimmed": true,
	"spriteSourceSize": {"x":96,"y":77,"w":104,"h":104},
	"sourceSize": {"w":300,"h":300},
	"pivot": {"x":0.5,"y":0.5}
},
{
	"filename": "zho_build10_born_0010.png",
	"frame": {"x":112,"y":224,"w":109,"h":109},
	"rotated": false,
	"trimmed": true,
	"spriteSourceSize": {"x":95,"y":74,"w":109,"h":109},
	"sourceSize": {"w":300,"h":300},
	"pivot": {"x":0.5,"y":0.5}
},
{
	"filename": "zho_build10_withers_0000.png",
	"frame": {"x":1,"y":333,"w":109,"h":109},
	"rotated": false,
	"trimmed": true,
	"spriteSourceSize": {"x":95,"y":74,"w":109,"h":109},
	"sourceSize": {"w":300,"h":300},
	"pivot": {"x":0.5,"y":0.5}
},
{
	"filename": "zho_build10_withers_0001.png",
	"frame": {"x":112,"y":445,"w":109,"h":108},
	"rotated": false,
	"trimmed": true,
	"spriteSourceSize": {"x":95,"y":75,"w":109,"h":108},
	"sourceSize": {"w":300,"h":300},
	"pivot": {"x":0.5,"y":0.5}
},
{
	"filename": "zho_build10_withers_0002.png",
	"frame": {"x":1,"y":554,"w":109,"h":108},
	"rotated": false,
	"trimmed": true,
	"spriteSourceSize": {"x":95,"y":75,"w":109,"h":108},
	"sourceSize": {"w":300,"h":300},
	"pivot": {"x":0.5,"y":0.5}
},
{
	"filename": "zho_build10_withers_0003.png",
	"frame": {"x":112,"y":335,"w":110,"h":108},
	"rotated": false,
	"trimmed": true,
	"spriteSourceSize": {"x":94,"y":75,"w":110,"h":108},
	"sourceSize": {"w":300,"h":300},
	"pivot": {"x":0.5,"y":0.5}
},
{
	"filename": "zho_build10_withers_0004.png",
	"frame": {"x":112,"y":555,"w":110,"h":107},
	"rotated": false,
	"trimmed": true,
	"spriteSourceSize": {"x":94,"y":76,"w":110,"h":107},
	"sourceSize": {"w":300,"h":300},
	"pivot": {"x":0.5,"y":0.5}
},
{
	"filename": "zho_build10_withers_0005.png",
	"frame": {"x":1,"y":664,"w":110,"h":107},
	"rotated": false,
	"trimmed": true,
	"spriteSourceSize": {"x":94,"y":76,"w":110,"h":107},
	"sourceSize": {"w":300,"h":300},
	"pivot": {"x":0.5,"y":0.5}
},
{
	"filename": "zho_build10_withers_0006.png",
	"frame": {"x":113,"y":664,"w":109,"h":107},
	"rotated": false,
	"trimmed": true,
	"spriteSourceSize": {"x":94,"y":76,"w":109,"h":107},
	"sourceSize": {"w":300,"h":300},
	"pivot": {"x":0.5,"y":0.5}
},
{
	"filename": "zho_build10_withers_0007.png",
	"frame": {"x":1,"y":773,"w":109,"h":107},
	"rotated": false,
	"trimmed": true,
	"spriteSourceSize": {"x":94,"y":77,"w":109,"h":107},
	"sourceSize": {"w":300,"h":300},
	"pivot": {"x":0.5,"y":0.5}
},
{
	"filename": "zho_build10_withers_0008.png",
	"frame": {"x":112,"y":773,"w":109,"h":107},
	"rotated": false,
	"trimmed": true,
	"spriteSourceSize": {"x":94,"y":77,"w":109,"h":107},
	"sourceSize": {"w":300,"h":300},
	"pivot": {"x":0.5,"y":0.5}
},
{
	"filename": "zho_build10_withers_0009.png",
	"frame": {"x":1,"y":882,"w":109,"h":107},
	"rotated": false,
	"trimmed": true,
	"spriteSourceSize": {"x":94,"y":77,"w":109,"h":107},
	"sourceSize": {"w":300,"h":300},
	"pivot": {"x":0.5,"y":0.5}
},
{
	"filename": "zho_build10_withers_0010.png",
	"frame": {"x":112,"y":882,"w":109,"h":107},
	"rotated": false,
	"trimmed": true,
	"spriteSourceSize": {"x":94,"y":77,"w":109,"h":107},
	"sourceSize": {"w":300,"h":300},
	"pivot": {"x":0.5,"y":0.5}
}],
"meta": {
	"app": "http://www.codeandweb.com/texturepacker",
	"version": "1.0",
	"image": "zho_build10.png",
	"format": "RGBA8888",
	"size": {"w":246,"h":1300},
	"scale": "1",
	"smartupdate": "$TexturePacker:SmartUpdate:67daf8d28359ab4123e3cff4a4ef64a4:10950656dd7c17abda4d23fb585fb2eb:2ddd544916a99d5bf03ba8ebad0bc5b3$"
}
}
