{"frames": {

"fed_un08_c050000.png":
{
	"frame": {"x":1,"y":75,"w":44,"h":33},
	"rotated": false,
	"trimmed": true,
	"spriteSourceSize": {"x":128,"y":129,"w":44,"h":33},
	"sourceSize": {"w":300,"h":300},
	"pivot": {"x":0.5,"y":0.5}
},
"fed_un08_c050001.png":
{
	"frame": {"x":1,"y":1,"w":44,"h":35},
	"rotated": false,
	"trimmed": true,
	"spriteSourceSize": {"x":128,"y":129,"w":44,"h":35},
	"sourceSize": {"w":300,"h":300},
	"pivot": {"x":0.5,"y":0.5}
},
"fed_un08_c050002.png":
{
	"frame": {"x":1,"y":38,"w":44,"h":35},
	"rotated": false,
	"trimmed": true,
	"spriteSourceSize": {"x":128,"y":129,"w":44,"h":35},
	"sourceSize": {"w":300,"h":300},
	"pivot": {"x":0.5,"y":0.5}
},
"fed_un08_c050003.png":
{
	"frame": {"x":47,"y":67,"w":42,"h":30},
	"rotated": false,
	"trimmed": true,
	"spriteSourceSize": {"x":130,"y":133,"w":42,"h":30},
	"sourceSize": {"w":300,"h":300},
	"pivot": {"x":0.5,"y":0.5}
},
"fed_un08_c050004.png":
{
	"frame": {"x":47,"y":1,"w":42,"h":31},
	"rotated": false,
	"trimmed": true,
	"spriteSourceSize": {"x":130,"y":133,"w":42,"h":31},
	"sourceSize": {"w":300,"h":300},
	"pivot": {"x":0.5,"y":0.5}
},
"fed_un08_c050005.png":
{
	"frame": {"x":91,"y":1,"w":42,"h":30},
	"rotated": false,
	"trimmed": true,
	"spriteSourceSize": {"x":130,"y":133,"w":42,"h":30},
	"sourceSize": {"w":300,"h":300},
	"pivot": {"x":0.5,"y":0.5}
},
"fed_un08_c050006.png":
{
	"frame": {"x":208,"y":36,"w":34,"h":32},
	"rotated": false,
	"trimmed": true,
	"spriteSourceSize": {"x":135,"y":130,"w":34,"h":32},
	"sourceSize": {"w":300,"h":300},
	"pivot": {"x":0.5,"y":0.5}
},
"fed_un08_c050007.png":
{
	"frame": {"x":172,"y":1,"w":34,"h":33},
	"rotated": false,
	"trimmed": true,
	"spriteSourceSize": {"x":135,"y":130,"w":34,"h":33},
	"sourceSize": {"w":300,"h":300},
	"pivot": {"x":0.5,"y":0.5}
},
"fed_un08_c050008.png":
{
	"frame": {"x":135,"y":1,"w":35,"h":33},
	"rotated": false,
	"trimmed": true,
	"spriteSourceSize": {"x":134,"y":130,"w":35,"h":33},
	"sourceSize": {"w":300,"h":300},
	"pivot": {"x":0.5,"y":0.5}
},
"fed_un08_c050009.png":
{
	"frame": {"x":393,"y":69,"w":28,"h":34},
	"rotated": false,
	"trimmed": true,
	"spriteSourceSize": {"x":136,"y":128,"w":28,"h":34},
	"sourceSize": {"w":300,"h":300},
	"pivot": {"x":0.5,"y":0.5}
},
"fed_un08_c050010.png":
{
	"frame": {"x":310,"y":1,"w":30,"h":34},
	"rotated": false,
	"trimmed": true,
	"spriteSourceSize": {"x":134,"y":128,"w":30,"h":34},
	"sourceSize": {"w":300,"h":300},
	"pivot": {"x":0.5,"y":0.5}
},
"fed_un08_c050011.png":
{
	"frame": {"x":244,"y":1,"w":31,"h":34},
	"rotated": false,
	"trimmed": true,
	"spriteSourceSize": {"x":133,"y":128,"w":31,"h":34},
	"sourceSize": {"w":300,"h":300},
	"pivot": {"x":0.5,"y":0.5}
},
"fed_un08_c050012.png":
{
	"frame": {"x":468,"y":28,"w":24,"h":36},
	"rotated": false,
	"trimmed": true,
	"spriteSourceSize": {"x":138,"y":128,"w":24,"h":36},
	"sourceSize": {"w":300,"h":300},
	"pivot": {"x":0.5,"y":0.5}
},
"fed_un08_c050013.png":
{
	"frame": {"x":440,"y":28,"w":26,"h":36},
	"rotated": false,
	"trimmed": true,
	"spriteSourceSize": {"x":136,"y":128,"w":26,"h":36},
	"sourceSize": {"w":300,"h":300},
	"pivot": {"x":0.5,"y":0.5}
},
"fed_un08_c050014.png":
{
	"frame": {"x":348,"y":37,"w":28,"h":36},
	"rotated": false,
	"trimmed": true,
	"spriteSourceSize": {"x":134,"y":128,"w":28,"h":36},
	"sourceSize": {"w":300,"h":300},
	"pivot": {"x":0.5,"y":0.5}
},
"fed_un08_c050015.png":
{
	"frame": {"x":406,"y":1,"w":28,"h":32},
	"rotated": false,
	"trimmed": true,
	"spriteSourceSize": {"x":136,"y":131,"w":28,"h":32},
	"sourceSize": {"w":300,"h":300},
	"pivot": {"x":0.5,"y":0.5}
},
"fed_un08_c050016.png":
{
	"frame": {"x":331,"y":87,"w":30,"h":32},
	"rotated": false,
	"trimmed": true,
	"spriteSourceSize": {"x":134,"y":131,"w":30,"h":32},
	"sourceSize": {"w":300,"h":300},
	"pivot": {"x":0.5,"y":0.5}
},
"fed_un08_c050017.png":
{
	"frame": {"x":298,"y":87,"w":31,"h":32},
	"rotated": false,
	"trimmed": true,
	"spriteSourceSize": {"x":133,"y":131,"w":31,"h":32},
	"sourceSize": {"w":300,"h":300},
	"pivot": {"x":0.5,"y":0.5}
},
"fed_un08_c050018.png":
{
	"frame": {"x":226,"y":93,"w":34,"h":26},
	"rotated": false,
	"trimmed": true,
	"spriteSourceSize": {"x":135,"y":135,"w":34,"h":26},
	"sourceSize": {"w":300,"h":300},
	"pivot": {"x":0.5,"y":0.5}
},
"fed_un08_c050019.png":
{
	"frame": {"x":312,"y":60,"w":34,"h":25},
	"rotated": false,
	"trimmed": true,
	"spriteSourceSize": {"x":135,"y":135,"w":34,"h":25},
	"sourceSize": {"w":300,"h":300},
	"pivot": {"x":0.5,"y":0.5}
},
"fed_un08_c050020.png":
{
	"frame": {"x":244,"y":37,"w":35,"h":25},
	"rotated": false,
	"trimmed": true,
	"spriteSourceSize": {"x":134,"y":135,"w":35,"h":25},
	"sourceSize": {"w":300,"h":300},
	"pivot": {"x":0.5,"y":0.5}
},
"fed_un08_c050021.png":
{
	"frame": {"x":47,"y":99,"w":42,"h":21},
	"rotated": false,
	"trimmed": true,
	"spriteSourceSize": {"x":130,"y":139,"w":42,"h":21},
	"sourceSize": {"w":300,"h":300},
	"pivot": {"x":0.5,"y":0.5}
},
"fed_un08_c050022.png":
{
	"frame": {"x":225,"y":70,"w":42,"h":21},
	"rotated": false,
	"trimmed": true,
	"spriteSourceSize": {"x":130,"y":138,"w":42,"h":21},
	"sourceSize": {"w":300,"h":300},
	"pivot": {"x":0.5,"y":0.5}
},
"fed_un08_c050023.png":
{
	"frame": {"x":181,"y":71,"w":42,"h":22},
	"rotated": false,
	"trimmed": true,
	"spriteSourceSize": {"x":130,"y":137,"w":42,"h":22},
	"sourceSize": {"w":300,"h":300},
	"pivot": {"x":0.5,"y":0.5}
},
"fed_un08_c050024.png":
{
	"frame": {"x":91,"y":97,"w":44,"h":22},
	"rotated": false,
	"trimmed": true,
	"spriteSourceSize": {"x":128,"y":138,"w":44,"h":22},
	"sourceSize": {"w":300,"h":300},
	"pivot": {"x":0.5,"y":0.5}
},
"fed_un08_c050025.png":
{
	"frame": {"x":135,"y":71,"w":44,"h":22},
	"rotated": false,
	"trimmed": true,
	"spriteSourceSize": {"x":128,"y":138,"w":44,"h":22},
	"sourceSize": {"w":300,"h":300},
	"pivot": {"x":0.5,"y":0.5}
},
"fed_un08_c050026.png":
{
	"frame": {"x":137,"y":95,"w":44,"h":22},
	"rotated": false,
	"trimmed": true,
	"spriteSourceSize": {"x":128,"y":138,"w":44,"h":22},
	"sourceSize": {"w":300,"h":300},
	"pivot": {"x":0.5,"y":0.5}
},
"fed_un08_c050027.png":
{
	"frame": {"x":269,"y":64,"w":41,"h":21},
	"rotated": false,
	"trimmed": true,
	"spriteSourceSize": {"x":128,"y":139,"w":41,"h":21},
	"sourceSize": {"w":300,"h":300},
	"pivot": {"x":0.5,"y":0.5}
},
"fed_un08_c050028.png":
{
	"frame": {"x":281,"y":37,"w":41,"h":21},
	"rotated": false,
	"trimmed": true,
	"spriteSourceSize": {"x":128,"y":138,"w":41,"h":21},
	"sourceSize": {"w":300,"h":300},
	"pivot": {"x":0.5,"y":0.5}
},
"fed_un08_c050029.png":
{
	"frame": {"x":183,"y":95,"w":41,"h":22},
	"rotated": false,
	"trimmed": true,
	"spriteSourceSize": {"x":128,"y":137,"w":41,"h":22},
	"sourceSize": {"w":300,"h":300},
	"pivot": {"x":0.5,"y":0.5}
},
"fed_un08_c050030.png":
{
	"frame": {"x":262,"y":93,"w":34,"h":26},
	"rotated": false,
	"trimmed": true,
	"spriteSourceSize": {"x":131,"y":135,"w":34,"h":26},
	"sourceSize": {"w":300,"h":300},
	"pivot": {"x":0.5,"y":0.5}
},
"fed_un08_c050031.png":
{
	"frame": {"x":436,"y":1,"w":34,"h":25},
	"rotated": false,
	"trimmed": true,
	"spriteSourceSize": {"x":131,"y":135,"w":34,"h":25},
	"sourceSize": {"w":300,"h":300},
	"pivot": {"x":0.5,"y":0.5}
},
"fed_un08_c050032.png":
{
	"frame": {"x":472,"y":1,"w":34,"h":25},
	"rotated": false,
	"trimmed": true,
	"spriteSourceSize": {"x":131,"y":135,"w":34,"h":25},
	"sourceSize": {"w":300,"h":300},
	"pivot": {"x":0.5,"y":0.5}
},
"fed_un08_c050033.png":
{
	"frame": {"x":410,"y":35,"w":28,"h":32},
	"rotated": false,
	"trimmed": true,
	"spriteSourceSize": {"x":136,"y":131,"w":28,"h":32},
	"sourceSize": {"w":300,"h":300},
	"pivot": {"x":0.5,"y":0.5}
},
"fed_un08_c050034.png":
{
	"frame": {"x":374,"y":1,"w":30,"h":32},
	"rotated": false,
	"trimmed": true,
	"spriteSourceSize": {"x":136,"y":131,"w":30,"h":32},
	"sourceSize": {"w":300,"h":300},
	"pivot": {"x":0.5,"y":0.5}
},
"fed_un08_c050035.png":
{
	"frame": {"x":378,"y":35,"w":30,"h":32},
	"rotated": false,
	"trimmed": true,
	"spriteSourceSize": {"x":136,"y":131,"w":30,"h":32},
	"sourceSize": {"w":300,"h":300},
	"pivot": {"x":0.5,"y":0.5}
},
"fed_un08_c050036.png":
{
	"frame": {"x":481,"y":66,"w":24,"h":36},
	"rotated": false,
	"trimmed": true,
	"spriteSourceSize": {"x":138,"y":128,"w":24,"h":36},
	"sourceSize": {"w":300,"h":300},
	"pivot": {"x":0.5,"y":0.5}
},
"fed_un08_c050037.png":
{
	"frame": {"x":453,"y":66,"w":26,"h":36},
	"rotated": false,
	"trimmed": true,
	"spriteSourceSize": {"x":138,"y":128,"w":26,"h":36},
	"sourceSize": {"w":300,"h":300},
	"pivot": {"x":0.5,"y":0.5}
},
"fed_un08_c050038.png":
{
	"frame": {"x":363,"y":75,"w":28,"h":36},
	"rotated": false,
	"trimmed": true,
	"spriteSourceSize": {"x":138,"y":128,"w":28,"h":36},
	"sourceSize": {"w":300,"h":300},
	"pivot": {"x":0.5,"y":0.5}
},
"fed_un08_c050039.png":
{
	"frame": {"x":423,"y":69,"w":28,"h":34},
	"rotated": false,
	"trimmed": true,
	"spriteSourceSize": {"x":136,"y":128,"w":28,"h":34},
	"sourceSize": {"w":300,"h":300},
	"pivot": {"x":0.5,"y":0.5}
},
"fed_un08_c050040.png":
{
	"frame": {"x":342,"y":1,"w":30,"h":34},
	"rotated": false,
	"trimmed": true,
	"spriteSourceSize": {"x":136,"y":128,"w":30,"h":34},
	"sourceSize": {"w":300,"h":300},
	"pivot": {"x":0.5,"y":0.5}
},
"fed_un08_c050041.png":
{
	"frame": {"x":277,"y":1,"w":31,"h":34},
	"rotated": false,
	"trimmed": true,
	"spriteSourceSize": {"x":136,"y":128,"w":31,"h":34},
	"sourceSize": {"w":300,"h":300},
	"pivot": {"x":0.5,"y":0.5}
},
"fed_un08_c050042.png":
{
	"frame": {"x":172,"y":36,"w":34,"h":33},
	"rotated": false,
	"trimmed": true,
	"spriteSourceSize": {"x":131,"y":130,"w":34,"h":33},
	"sourceSize": {"w":300,"h":300},
	"pivot": {"x":0.5,"y":0.5}
},
"fed_un08_c050043.png":
{
	"frame": {"x":208,"y":1,"w":34,"h":33},
	"rotated": false,
	"trimmed": true,
	"spriteSourceSize": {"x":131,"y":130,"w":34,"h":33},
	"sourceSize": {"w":300,"h":300},
	"pivot": {"x":0.5,"y":0.5}
},
"fed_un08_c050044.png":
{
	"frame": {"x":135,"y":36,"w":35,"h":33},
	"rotated": false,
	"trimmed": true,
	"spriteSourceSize": {"x":131,"y":130,"w":35,"h":33},
	"sourceSize": {"w":300,"h":300},
	"pivot": {"x":0.5,"y":0.5}
},
"fed_un08_c050045.png":
{
	"frame": {"x":91,"y":33,"w":42,"h":30},
	"rotated": false,
	"trimmed": true,
	"spriteSourceSize": {"x":128,"y":133,"w":42,"h":30},
	"sourceSize": {"w":300,"h":300},
	"pivot": {"x":0.5,"y":0.5}
},
"fed_un08_c050046.png":
{
	"frame": {"x":47,"y":34,"w":42,"h":31},
	"rotated": false,
	"trimmed": true,
	"spriteSourceSize": {"x":128,"y":133,"w":42,"h":31},
	"sourceSize": {"w":300,"h":300},
	"pivot": {"x":0.5,"y":0.5}
},
"fed_un08_c050047.png":
{
	"frame": {"x":91,"y":65,"w":42,"h":30},
	"rotated": false,
	"trimmed": true,
	"spriteSourceSize": {"x":128,"y":133,"w":42,"h":30},
	"sourceSize": {"w":300,"h":300},
	"pivot": {"x":0.5,"y":0.5}
}},
"meta": {
	"app": "http://www.codeandweb.com/texturepacker",
	"version": "1.0",
	"image": "fed_unit08_c05.png",
	"format": "RGBA8888",
	"size": {"w":510,"h":121},
	"scale": "1",
	"smartupdate": "$TexturePacker:SmartUpdate:9614bf1572d97c1a762d588557d64cb1:02bcfa03b008a9016ea621e9bb2c529a:3db8d5780dc7e84db7ef6cc6a9241fa6$"
}
}
