{"frames": {

"weapon01.png":
{
	"frame": {"x":1,"y":340,"w":13,"h":30},
	"rotated": false,
	"trimmed": true,
	"spriteSourceSize": {"x":5,"y":6,"w":13,"h":30},
	"sourceSize": {"w":22,"h":45},
	"pivot": {"x":0.5,"y":0.5}
},
"weapon02.png":
{
	"frame": {"x":1,"y":372,"w":13,"h":30},
	"rotated": false,
	"trimmed": true,
	"spriteSourceSize": {"x":5,"y":5,"w":13,"h":30},
	"sourceSize": {"w":22,"h":45},
	"pivot": {"x":0.5,"y":0.5}
},
"weapon03.png":
{
	"frame": {"x":1,"y":258,"w":13,"h":41},
	"rotated": false,
	"trimmed": true,
	"spriteSourceSize": {"x":5,"y":1,"w":13,"h":41},
	"sourceSize": {"w":22,"h":45},
	"pivot": {"x":0.5,"y":0.5}
},
"weapon04.png":
{
	"frame": {"x":1,"y":404,"w":12,"h":25},
	"rotated": false,
	"trimmed": true,
	"spriteSourceSize": {"x":5,"y":10,"w":12,"h":25},
	"sourceSize": {"w":22,"h":45},
	"pivot": {"x":0.5,"y":0.5}
},
"weapon05.png":
{
	"frame": {"x":1,"y":55,"w":18,"h":35},
	"rotated": false,
	"trimmed": true,
	"spriteSourceSize": {"x":2,"y":6,"w":18,"h":35},
	"sourceSize": {"w":22,"h":45},
	"pivot": {"x":0.5,"y":0.5}
},
"weapon06.png":
{
	"frame": {"x":1,"y":301,"w":13,"h":37},
	"rotated": false,
	"trimmed": true,
	"spriteSourceSize": {"x":5,"y":3,"w":13,"h":37},
	"sourceSize": {"w":22,"h":45},
	"pivot": {"x":0.5,"y":0.5}
},
"weapon07.png":
{
	"frame": {"x":1,"y":130,"w":17,"h":30},
	"rotated": false,
	"trimmed": true,
	"spriteSourceSize": {"x":3,"y":7,"w":17,"h":30},
	"sourceSize": {"w":22,"h":45},
	"pivot": {"x":0.5,"y":0.5}
},
"weapon08.png":
{
	"frame": {"x":1,"y":162,"w":17,"h":30},
	"rotated": false,
	"trimmed": true,
	"spriteSourceSize": {"x":3,"y":8,"w":17,"h":30},
	"sourceSize": {"w":22,"h":45},
	"pivot": {"x":0.5,"y":0.5}
},
"weapon09.png":
{
	"frame": {"x":1,"y":194,"w":17,"h":30},
	"rotated": false,
	"trimmed": true,
	"spriteSourceSize": {"x":3,"y":9,"w":17,"h":30},
	"sourceSize": {"w":22,"h":45},
	"pivot": {"x":0.5,"y":0.5}
},
"weapon10.png":
{
	"frame": {"x":1,"y":1,"w":21,"h":25},
	"rotated": false,
	"trimmed": true,
	"spriteSourceSize": {"x":1,"y":12,"w":21,"h":25},
	"sourceSize": {"w":22,"h":45},
	"pivot": {"x":0.5,"y":0.5}
},
"weapon11.png":
{
	"frame": {"x":1,"y":28,"w":21,"h":25},
	"rotated": false,
	"trimmed": true,
	"spriteSourceSize": {"x":1,"y":10,"w":21,"h":25},
	"sourceSize": {"w":22,"h":45},
	"pivot": {"x":0.5,"y":0.5}
},
"weapon12.png":
{
	"frame": {"x":1,"y":92,"w":17,"h":36},
	"rotated": false,
	"trimmed": true,
	"spriteSourceSize": {"x":3,"y":7,"w":17,"h":36},
	"sourceSize": {"w":22,"h":45},
	"pivot": {"x":0.5,"y":0.5}
},
"weapon13.png":
{
	"frame": {"x":1,"y":226,"w":17,"h":30},
	"rotated": false,
	"trimmed": true,
	"spriteSourceSize": {"x":3,"y":8,"w":17,"h":30},
	"sourceSize": {"w":22,"h":45},
	"pivot": {"x":0.5,"y":0.5}
},
"weapon14.png":
{
	"frame": {"x":1,"y":431,"w":11,"h":11},
	"rotated": false,
	"trimmed": true,
	"spriteSourceSize": {"x":6,"y":17,"w":11,"h":11},
	"sourceSize": {"w":22,"h":45},
	"pivot": {"x":0.5,"y":0.5}
},
"weapon15.png":
{
	"frame": {"x":1,"y":444,"w":9,"h":21},
	"rotated": false,
	"trimmed": true,
	"spriteSourceSize": {"x":7,"y":14,"w":9,"h":21},
	"sourceSize": {"w":22,"h":45},
	"pivot": {"x":0.5,"y":0.5}
},
"weapon16.png":
{
	"frame": {"x":12,"y":444,"w":10,"h":17},
	"rotated": false,
	"trimmed": true,
	"spriteSourceSize": {"x":6,"y":14,"w":10,"h":17},
	"sourceSize": {"w":22,"h":45},
	"pivot": {"x":0.5,"y":0.5}
}},
"meta": {
	"app": "http://www.codeandweb.com/texturepacker",
	"version": "1.0",
	"image": "weapon_beams.png",
	"format": "RGBA8888",
	"size": {"w":23,"h":466},
	"scale": "1",
	"smartupdate": "$TexturePacker:SmartUpdate:99b986efb8cc63e96a0b8c7c0fda7a68:bde793fee199d5292335d0f49b9f0981:48b219993e31932a4e99e677f5bd093c$"
}
}
